gpiooutputtest.py
gpiooutputtest-0.0.2.dist-info/METADATA
gpiooutputtest-0.0.2.dist-info/WHEEL
gpiooutputtest-0.0.2.dist-info/entry_points.txt
gpiooutputtest-0.0.2.dist-info/top_level.txt
gpiooutputtest-0.0.2.dist-info/RECORD
