Metadata-Version: 2.1
Name: gpiooutputtest
Version: 0.0.2
Summary: Individually test the given GPIO output pins
Author: Joe Greaves
Project-URL: Homepage, https://github.com/Grvs44/gpiooutputtest
Classifier: Programming Language :: Python :: 3
Classifier: License :: OSI Approved :: BSD License
Classifier: Operating System :: POSIX :: Linux
Requires-Python: <4,>=3.11
Requires-Dist: RPi.GPIO (>=0.7.1)
